<Community Config>
  <Community>
    <Name>Comm 1</Name>
    <Template>Four Agent</Template>
    <Demand>10</Demand>
    <Production>5</Production>
    <Supplies>
      <Supply Community>Comm 2</Supply Community>
    </Supplies>
    <Geography>
      <Latitute>25</Latitute>
      <Longitude>52</Longitude>
    </Geography>
  </Community>
  <Community>
    <Name>Comm 2</Name>
    <Template>Four Agent</Template>
    <Demand>23</Demand>
    <Production>13</Production>
    <Supplies>
      <Supply Community>Comm 3</Supply Community>
    </Supplies>
    <Geography>
      <Latitute>45</Latitute>
      <Longitude>75</Longitude>
    </Geography>
  </Community>
  <Community>
    <Name>Comm 3</Name>
    <Template>Four Agent</Template>
    <Demand>3</Demand>
    <Production>43</Production>
    <Supplies/>
    <Geography>
      <Latitute>145</Latitute>
      <Longitude>175</Longitude>
    </Geography>
  </Community>
</Community Config>
